{
  "frames": {
    "Untitled-2": {
      "frame": {
        "x": 4,
        "y": 4,
        "w": 648,
        "h": 1402
      },
      "rotated": false,
      "trimmed": false,
      "spriteSourceSize": {
        "x": 0,
        "y": 0,
        "w": 648,
        "h": 1402
      },
      "sourceSize": {
        "w": 648,
        "h": 1402
      },
      "pivot": {
        "x": 0.5,
        "y": 0.5
      }
    },
    "s_fx_stars_01": {
      "frame": {
        "x": 4,
        "y": 1414,
        "w": 166,
        "h": 166
      },
      "rotated": false,
      "trimmed": false,
      "spriteSourceSize": {
        "x": 0,
        "y": 0,
        "w": 166,
        "h": 166
      },
      "sourceSize": {
        "w": 166,
        "h": 166
      },
      "pivot": {
        "x": 0.5,
        "y": 0.5
      }
    },
    "s_fx_stars_02": {
      "frame": {
        "x": 4,
        "y": 1588,
        "w": 166,
        "h": 166
      },
      "rotated": false,
      "trimmed": false,
      "spriteSourceSize": {
        "x": 0,
        "y": 0,
        "w": 166,
        "h": 166
      },
      "sourceSize": {
        "w": 166,
        "h": 166
      },
      "pivot": {
        "x": 0.5,
        "y": 0.5
      }
    },
    "s_fx_stars_03": {
      "frame": {
        "x": 4,
        "y": 1762,
        "w": 166,
        "h": 166
      },
      "rotated": false,
      "trimmed": false,
      "spriteSourceSize": {
        "x": 0,
        "y": 0,
        "w": 166,
        "h": 166
      },
      "sourceSize": {
        "w": 166,
        "h": 166
      },
      "pivot": {
        "x": 0.5,
        "y": 0.5
      }
    },
    "s_fx_stars_04": {
      "frame": {
        "x": 178,
        "y": 1414,
        "w": 166,
        "h": 166
      },
      "rotated": false,
      "trimmed": false,
      "spriteSourceSize": {
        "x": 0,
        "y": 0,
        "w": 166,
        "h": 166
      },
      "sourceSize": {
        "w": 166,
        "h": 166
      },
      "pivot": {
        "x": 0.5,
        "y": 0.5
      }
    },
    "s_fx_stars_05": {
      "frame": {
        "x": 178,
        "y": 1588,
        "w": 166,
        "h": 166
      },
      "rotated": false,
      "trimmed": false,
      "spriteSourceSize": {
        "x": 0,
        "y": 0,
        "w": 166,
        "h": 166
      },
      "sourceSize": {
        "w": 166,
        "h": 166
      },
      "pivot": {
        "x": 0.5,
        "y": 0.5
      }
    },
    "s_fx_stars_06": {
      "frame": {
        "x": 178,
        "y": 1762,
        "w": 166,
        "h": 166
      },
      "rotated": false,
      "trimmed": false,
      "spriteSourceSize": {
        "x": 0,
        "y": 0,
        "w": 166,
        "h": 166
      },
      "sourceSize": {
        "w": 166,
        "h": 166
      },
      "pivot": {
        "x": 0.5,
        "y": 0.5
      }
    },
    "s_fx_stars_07": {
      "frame": {
        "x": 352,
        "y": 1414,
        "w": 166,
        "h": 166
      },
      "rotated": false,
      "trimmed": false,
      "spriteSourceSize": {
        "x": 0,
        "y": 0,
        "w": 166,
        "h": 166
      },
      "sourceSize": {
        "w": 166,
        "h": 166
      },
      "pivot": {
        "x": 0.5,
        "y": 0.5
      }
    },
    "s_fx_stars_08": {
      "frame": {
        "x": 352,
        "y": 1588,
        "w": 166,
        "h": 166
      },
      "rotated": false,
      "trimmed": false,
      "spriteSourceSize": {
        "x": 0,
        "y": 0,
        "w": 166,
        "h": 166
      },
      "sourceSize": {
        "w": 166,
        "h": 166
      },
      "pivot": {
        "x": 0.5,
        "y": 0.5
      }
    }
  },
  "meta": {
    "app": "http://github.com/odrick/free-tex-packer-core",
    "version": "0.3.4",
    "image": "stareffect.png",
    "format": "RGBA8888",
    "size": {
      "w": 656,
      "h": 1932
    },
    "scale": 0.5538461538461539
  }
}
