{
  "ID": "decorative_feedingtrough",
  "nameKey": "decorative_feedingtrough",
  "npcIconKey": "icon_character_worker",
  "movable": true,
  "defaultLevel": 1,
  "defaultState": 0,
  "levels": [
    {
      "visualKeys": {
        "upgrading": "obj_decorateive_feedingtrough_broken",
        "active": "obj_decorateive_feedingtrough"
      },
      "upgradeCost": [
        { "blueprintID": "tool_3", "amount": 1 },
        { "blueprintID": "tool_4", "amount": 1 }
      ],
      "discoverOverlay": {
        "atlasKey": "repair_sweets",
        "messageKey": "decorative_object_introduction",
        "oldImageKey": "obj_decorateive_feedingtrough_repair",
        "newImageKey": "obj_decorateive_feedingtrough_repair"
      },
      "upgradeOverlay": {
        "atlasKey": "repair_sweets",
        "messageKey": "repaired_message",
        "oldImageKey": "obj_decorateive_feedingtrough_repair",
        "newImageKey": "obj_decorateive_feedingtrough_unlock"
      }
    }
  ],
  "isWorkshop": false,
  "cooldown": 3
}
